.git_archival.txt
.gitattributes
.gitignore
.pre-commit-config.yaml
LICENSE
README.md
pyproject.toml
setup.cfg
setup.py
docker/README.md
docker/cpu.Dockerfile
docker/gpu.Dockerfile
nondefaced_detector/__init__.py
nondefaced_detector/_version.py
nondefaced_detector/inference.py
nondefaced_detector/prediction.py
nondefaced_detector/preprocess.py
nondefaced_detector/utils.py
nondefaced_detector.egg-info/PKG-INFO
nondefaced_detector.egg-info/SOURCES.txt
nondefaced_detector.egg-info/dependency_links.txt
nondefaced_detector.egg-info/entry_points.txt
nondefaced_detector.egg-info/requires.txt
nondefaced_detector.egg-info/top_level.txt
nondefaced_detector/cli/__init__.py
nondefaced_detector/cli/main.py
nondefaced_detector/cli/tests/main_test.py
nondefaced_detector/dataloaders/__init__.py
nondefaced_detector/dataloaders/dataset.py
nondefaced_detector/helpers/__init__.py
nondefaced_detector/helpers/utils.py
nondefaced_detector/models/__init__.py
nondefaced_detector/models/model.py
nondefaced_detector/preprocessing/__init__.py
nondefaced_detector/preprocessing/conform.py
nondefaced_detector/preprocessing/normalization.py
nondefaced_detector/tests/__init__.py
nondefaced_detector/tests/utils_test.py
nondefaced_detector/training/__init__.py
nondefaced_detector/training/training.py