Metadata-Version: 2.1
Name: nondefaced-detector
Version: 0.1.3
Summary: A package to detect if an MRI Volume has been defaced.
Home-page: https://github.com/poldracklab/nondefaced-detector
Author: Nondefaced Detector Developers
Author-email: shashankbansal56@gmail.com
License: Apache License, 2.0
Project-URL: Bug Tracker, https://github.com/poldracklab/nondefaced-detector/issues
Platform: UNKNOWN
Classifier: Environment :: Console
Classifier: Intended Audience :: Developers
Classifier: Intended Audience :: Education
Classifier: Intended Audience :: Healthcare Industry
Classifier: Intended Audience :: Science/Research
Classifier: License :: OSI Approved :: Apache Software License
Classifier: Operating System :: OS Independent
Classifier: Programming Language :: Python :: 3
Classifier: Programming Language :: Python :: 3 :: Only
Classifier: Programming Language :: Python :: 3.6
Classifier: Programming Language :: Python :: 3.7
Classifier: Topic :: Scientific/Engineering :: Artificial Intelligence
Classifier: Topic :: Software Development
Classifier: Topic :: Software Development :: Libraries :: Python Modules
Requires-Python: >=3.6
Provides-Extra: cpu
Provides-Extra: gpu
Provides-Extra: dev
